query_profiler/__init__.py
query_profiler/middleware.py
bear_django_query_profiler-0.1.0.dist-info/METADATA
bear_django_query_profiler-0.1.0.dist-info/WHEEL
bear_django_query_profiler-0.1.0.dist-info/top_level.txt
bear_django_query_profiler-0.1.0.dist-info/RECORD
