Metadata-Version: 2.4
Name: bear-django-query-profiler
Version: 0.1.0
Summary: A simple Django middleware to log SQL queries during development.
Author-email: Bohdan Riabunets <bearablyk@gmail.com>
License-Expression: MIT
Project-URL: Homepage, https://github.com/bearablyk/django-query-profiler
Project-URL: Issues, https://github.com/bearablyk/django-query-profiler/issues
Classifier: Programming Language :: Python :: 3
Classifier: Operating System :: OS Independent
Classifier: Framework :: Django
Classifier: Environment :: Web Environment
Classifier: Intended Audience :: Developers
Classifier: Topic :: System :: Logging
Requires-Python: >=3.8
Requires-Dist: Django>=3.2
